fastapi_auth_jwt/__init__.py
fastapi_auth_jwt/backend.py
fastapi_auth_jwt/middleware.py
fastapi_auth_jwt/config/__init__.py
fastapi_auth_jwt/config/auth_token.py
fastapi_auth_jwt/config/storage.py
fastapi_auth_jwt/config/storage_type.py
fastapi_auth_jwt/config/types.py
fastapi_auth_jwt/config/user_schema.py
fastapi_auth_jwt/repository/__init__.py
fastapi_auth_jwt/repository/base.py
fastapi_auth_jwt/repository/factory.py
fastapi_auth_jwt/repository/local.py
fastapi_auth_jwt/repository/redis.py
fastapi_auth_jwt/utils/__init__.py
fastapi_auth_jwt/utils/jwt_token.py
fastapi_auth_jwt/utils/time_helpers.py
fastapi_auth_jwt-1.0.0.dist-info/METADATA
fastapi_auth_jwt-1.0.0.dist-info/WHEEL
fastapi_auth_jwt-1.0.0.dist-info/licenses/LICENSE
fastapi_auth_jwt-1.0.0.dist-info/RECORD
